LICENSE
MANIFEST.in
README.md
VERSION
requirements.txt
setup.py
src/txrestserver/__init__.py
src/txrestserver/rest_server.py
src/txrestserver.egg-info/PKG-INFO
src/txrestserver.egg-info/SOURCES.txt
src/txrestserver.egg-info/dependency_links.txt
src/txrestserver.egg-info/requires.txt
src/txrestserver.egg-info/top_level.txt
src/txrestserver/access/__init__.py
src/txrestserver/access/access.py
src/txrestserver/access/basic_access.py
src/txrestserver/access/digest_access.py
src/txrestserver/access/tls_access.py
src/txrestserver/realm/__init__.py
src/txrestserver/realm/checkers.py
src/txrestserver/realm/realm.py
src/txrestserver/txrestapi/__init__.py
src/txrestserver/txrestapi/json_resource.py
src/txrestserver/txrestapi/methods.py
src/txrestserver/txrestapi/resource.py
src/txrestserver/txrestapi/service.py
src/txrestserver/txrestapi/test.py
src/txrestserver/txrestapi/tests.py
test/test_as_root.py