Metadata-Version: 2.1
Name: txrestserver
Version: 0.4.2
Summary: A simple REST server for twisted-python with access authentication support
Home-page: https://github.com/cboling/txrestserver
Author: Chip Boling
Author-email: chip@bcsw.net
License: UNKNOWN
Platform: UNKNOWN
Classifier: Development Status :: 3 - Alpha
Classifier: Intended Audience :: Developers
Classifier: Topic :: Software Development :: Libraries
Classifier: Topic :: Internet :: WWW/HTTP :: HTTP Servers
Classifier: License :: OSI Approved :: Apache Software License
Classifier: Framework :: Twisted
Classifier: Programming Language :: Python :: 3.6
Classifier: Programming Language :: Python :: 3.7
Classifier: Programming Language :: Python :: 3.8
Requires-Python: >=3.6
